{
  "id": "id-775e583d-03aa-484b-84db-1c021798c227",
  "cid": "holotapes_overseers_log_15_the_log_is_near_the_site_charlie_elevator_a_1213.99599_2047.12500_2qv78j9z",
  "category": "holotapes",
  "desc": "Overseers log – #15 The log is near the Site Charlie elevator at the R&G Processing Services. This is in the Savage Divide region of the map at the railway intersection near Spruce Knob.\nGrid E3 (X: 2047.1, Y: 1214)\nSubmitted By MrCrazy",
  "lat": 1213.9959945750452,
  "lng": 2047.125,
  "icon": "📀",
  "addedTime": 1778931395548,
  "locked": true,
  "isPostcard": false,
  "isTemp": false,
  "startTime": null,
  "keepBtnBound": false,
  "userEdited": false,
  "wasCommunityKept": false,
  "isCommunity": true
}