{
  "id": "id-3f5e455d-5bc2-4b92-b0d5-463bfbb4f720",
  "cid": "misc_12345_grid_b1_x_455_y_306_306.00000_455.00000_fbb4f720",
  "category": "misc",
  "desc": "12345. Grid B1 (X: 625, Y: 294.8)\nSubmitted By Anonymous Wastelander",
  "lat": 294.84991559157606,
  "lng": 625.0031483671959,
  "icon": "📝",
  "addedTime": 1777693061409,
  "locked": true,
  "isPostcard": false,
  "isTemp": false,
  "startTime": null,
  "keepBtnBound": false,
  "userEdited": false,
  "wasCommunityKept": false,
  "isCommunity": true
}